promobot_appeal_processing/__about__.py
promobot_appeal_processing/__init__.py
promobot_appeal_processing/config.py
promobot_appeal_processing/main.py
promobot_appeal_processing/model.py
promobot_appeal_processing/structures.py
promobot_appeal_processing/geography/__init__.py
promobot_appeal_processing/geography/main.py
promobot_appeal_processing/geography/model.py
promobot_appeal_processing-1.0.0.dist-info/METADATA
promobot_appeal_processing-1.0.0.dist-info/WHEEL
promobot_appeal_processing-1.0.0.dist-info/licenses/LICENSE
promobot_appeal_processing-1.0.0.dist-info/RECORD
